<annotation>
	<folder>concombres</folder>
	<filename>187.png</filename>
	<path>/home/kevin/Bureau/concombres/187.png</path>
	<source>
		<database>Unknown</database>
	</source>
	<size>
		<width>640</width>
		<height>480</height>
		<depth>3</depth>
	</size>
	<segmented>0</segmented>
	<object>
		<name>concombre</name>
		<pose>Unspecified</pose>
		<truncated>1</truncated>
		<difficult>0</difficult>
		<bndbox>
			<xmin>431</xmin>
			<ymin>413</ymin>
			<xmax>475</xmax>
			<ymax>480</ymax>
		</bndbox>
	</object>
	<object>
		<name>concombre</name>
		<pose>Unspecified</pose>
		<truncated>0</truncated>
		<difficult>0</difficult>
		<bndbox>
			<xmin>284</xmin>
			<ymin>158</ymin>
			<xmax>325</xmax>
			<ymax>386</ymax>
		</bndbox>
	</object>
</annotation>
